{
  "total": 120,
  "movies": [
    {
      "id": "771306093",
      "title": "The Good Dinosaur",
      "year": 2015,
      "mpaa_rating": "PG",
      "runtime": 100,
      "critics_consensus": "",
      "release_dates": {
        "theater": "2015-11-25"
      },
      "ratings": {
        "critics_rating": "Certified Fresh",
        "critics_score": 76,
        "audience_rating": "Upright",
        "audience_score": 74
      },
      "synopsis": "\"The Good Dinosaur\" asks the question: What if the asteroid that forever changed life on Earth missed the planet completely and giant dinosaurs never became extinct? Pixar Animation Studios takes you on an epic journey into the world of dinosaurs where an Apatosaurus named Arlo makes an unlikely human friend. While traveling through a harsh and mysterious landscape, Arlo learns the power of confronting his fears and discovers what he is truly capable of. (C) Disney",
      "posters": {
        "thumbnail": "http://resizing.flixster.com/QPxjgHkOs9puYxQDL5P-WA65ONc=/54x80/dkpu1ddg7pbsk.cloudfront.net/movie/11/20/70/11207072_ori.jpg",
        "profile": "http://resizing.flixster.com/QPxjgHkOs9puYxQDL5P-WA65ONc=/54x80/dkpu1ddg7pbsk.cloudfront.net/movie/11/20/70/11207072_ori.jpg",
        "detailed": "http://resizing.flixster.com/QPxjgHkOs9puYxQDL5P-WA65ONc=/54x80/dkpu1ddg7pbsk.cloudfront.net/movie/11/20/70/11207072_ori.jpg",
        "original": "http://resizing.flixster.com/QPxjgHkOs9puYxQDL5P-WA65ONc=/54x80/dkpu1ddg7pbsk.cloudfront.net/movie/11/20/70/11207072_ori.jpg"
      },
      "abridged_cast": [
        {
          "name": "Raymond Ochoa",
          "id": "770829316",
          "characters": [
            "Arlo"
          ]
        },
        {
          "name": "Jeffrey Wright",
          "id": "162653065",
          "characters": [
            "Poppa"
          ]
        },
        {
          "name": "Frances McDormand",
          "id": "162654734",
          "characters": [
            "Momma"
          ]
        },
        {
          "name": "Steve Zahn",
          "id": "162652352",
          "characters": [
            "Thunderclap"
          ]
        },
        {
          "name": "A.J. Buckley",
          "id": "326392926",
          "characters": [
            "Nash"
          ]
        }
      ],
      "alternate_ids": {
        "imdb": "1979388"
      },
      "links": {
        "self": "http://api.rottentomatoes.com/api/public/v1.0/movies/771306093.json",
        "alternate": "http://www.rottentomatoes.com/m/the_good_dinosaur/",
        "cast": "http://api.rottentomatoes.com/api/public/v1.0/movies/771306093/cast.json",
        "reviews": "http://api.rottentomatoes.com/api/public/v1.0/movies/771306093/reviews.json",
        "similar": "http://api.rottentomatoes.com/api/public/v1.0/movies/771306093/similar.json"
      }
    },
    {
      "id": "771312089",
      "title": "The Hunger Games: Mockingjay - Part 2",
      "year": 2015,
      "mpaa_rating": "PG-13",
      "runtime": 136,
      "critics_consensus": "",
      "release_dates": {
        "theater": "2015-11-20"
      },
      "ratings": {
        "critics_rating": "Fresh",
        "critics_score": 71,
        "audience_rating": "Upright",
        "audience_score": 73
      },
      "synopsis": "The second half of Suzanne Collins' final Hunger Games book is adapted in this Lionsgate production. ~ Jeremy Wheeler, Rovi",
      "posters": {
        "thumbnail": "http://resizing.flixster.com/nim-D7-9jGbUZS5wczNes_PmWyI=/53x81/dkpu1ddg7pbsk.cloudfront.net/movie/11/20/29/11202951_ori.jpg",
        "profile": "http://resizing.flixster.com/nim-D7-9jGbUZS5wczNes_PmWyI=/53x81/dkpu1ddg7pbsk.cloudfront.net/movie/11/20/29/11202951_ori.jpg",
        "detailed": "http://resizing.flixster.com/nim-D7-9jGbUZS5wczNes_PmWyI=/53x81/dkpu1ddg7pbsk.cloudfront.net/movie/11/20/29/11202951_ori.jpg",
        "original": "http://resizing.flixster.com/nim-D7-9jGbUZS5wczNes_PmWyI=/53x81/dkpu1ddg7pbsk.cloudfront.net/movie/11/20/29/11202951_ori.jpg"
      },
      "abridged_cast": [
        {
          "name": "Jennifer Lawrence",
          "id": "770800260",
          "characters": [
            "Katniss Everdeen"
          ]
        },
        {
          "name": "Julianne Moore",
          "id": "162654248",
          "characters": [
            "President Alma Coin"
          ]
        },
        {
          "name": "Gwendoline Christie",
          "id": "771060732",
          "characters": [
            "Commander Lyme"
          ]
        },
        {
          "name": "Josh Hutcherson",
          "id": "162654356",
          "characters": [
            "Peeta Mellark"
          ]
        },
        {
          "name": "Robert Knepper",
          "id": "162707688",
          "characters": [
            "Antonius"
          ]
        }
      ],
      "links": {
        "self": "http://api.rottentomatoes.com/api/public/v1.0/movies/771312089.json",
        "alternate": "http://www.rottentomatoes.com/m/the_hunger_games_mockingjay_part_2/",
        "cast": "http://api.rottentomatoes.com/api/public/v1.0/movies/771312089/cast.json",
        "reviews": "http://api.rottentomatoes.com/api/public/v1.0/movies/771312089/reviews.json",
        "similar": "http://api.rottentomatoes.com/api/public/v1.0/movies/771312089/similar.json"
      }
    },
    {
      "id": "771318152",
      "title": "The Peanuts Movie",
      "year": 2015,
      "mpaa_rating": "G",
      "runtime": 92,
      "critics_consensus": "",
      "release_dates": {
        "theater": "2015-11-06"
      },
      "ratings": {
        "critics_rating": "Certified Fresh",
        "critics_score": 86,
        "audience_rating": "Upright",
        "audience_score": 83
      },
      "synopsis": "Charlie Brown, Snoopy, Lucy, Linus and the rest of the beloved \"Peanuts\" gang make their big-screen debut, like they've never been seen before, in state of the art 3D animation. Charlie Brown, the world's most beloved underdog, embarks upon an epic and heroic quest, while his best pal, the lovable beagle Snoopy, takes to the skies to pursue his arch-nemesis, the Red Baron. From the imagination of Charles M. Schulz and the creators of the ICE AGE films, THE PEANUTS MOVIE will prove that every underdog has his day. (C) Fox",
      "posters": {
        "thumbnail": "http://resizing.flixster.com/v93Rn6_ysacfO0sVDyWe2-0ZPrs=/54x80/dkpu1ddg7pbsk.cloudfront.net/movie/11/19/14/11191451_ori.jpg",
        "profile": "http://resizing.flixster.com/v93Rn6_ysacfO0sVDyWe2-0ZPrs=/54x80/dkpu1ddg7pbsk.cloudfront.net/movie/11/19/14/11191451_ori.jpg",
        "detailed": "http://resizing.flixster.com/v93Rn6_ysacfO0sVDyWe2-0ZPrs=/54x80/dkpu1ddg7pbsk.cloudfront.net/movie/11/19/14/11191451_ori.jpg",
        "original": "http://resizing.flixster.com/v93Rn6_ysacfO0sVDyWe2-0ZPrs=/54x80/dkpu1ddg7pbsk.cloudfront.net/movie/11/19/14/11191451_ori.jpg"
      },
      "abridged_cast": [
        {
          "name": "Noah Schnapp",
          "id": "771656761",
          "characters": [
            "Charlie Brown"
          ]
        },
        {
          "name": "Hadley Belle Miller",
          "id": "771656762",
          "characters": [
            "Lucy van Pelt"
          ]
        },
        {
          "name": "Alexander Garfin",
          "id": "771656763",
          "characters": [
            "Linus van Pelt"
          ]
        },
        {
          "name": "Mariel Sheets",
          "id": "771656764",
          "characters": [
            "Sally Brown"
          ]
        },
        {
          "name": "Bill Melendez",
          "id": "162657046",
          "characters": [
            "Snoopy/Woodstock"
          ]
        }
      ],
      "alternate_ids": {
        "imdb": "2452042"
      },
      "links": {
        "self": "http://api.rottentomatoes.com/api/public/v1.0/movies/771318152.json",
        "alternate": "http://www.rottentomatoes.com/m/the_peanuts_movie/",
        "cast": "http://api.rottentomatoes.com/api/public/v1.0/movies/771318152/cast.json",
        "reviews": "http://api.rottentomatoes.com/api/public/v1.0/movies/771318152/reviews.json",
        "similar": "http://api.rottentomatoes.com/api/public/v1.0/movies/771318152/similar.json"
      }
    },
    {
      "id": "771413507",
      "title": "Creed",
      "year": 2015,
      "mpaa_rating": "PG-13",
      "runtime": 132,
      "critics_consensus": "",
      "release_dates": {
        "theater": "2015-11-25"
      },
      "ratings": {
        "critics_rating": "Certified Fresh",
        "critics_score": 92,
        "audience_rating": "Upright",
        "audience_score": 96
      },
      "synopsis": "Adonis Johnson never knew his famous father,world heavy weight champion Apollo Creed, who died before he was born. Still, there's no denying that boxing is in his blood, so Adonis heads to Philadelphia, the site of Apollo Creed's legendary match with a tough upstart named Rocky Balboa. Rocky sees in Adonis the strength and determination he had known in Apollo - the fierce rival who became his closest friend.",
      "posters": {
        "thumbnail": "http://resizing.flixster.com/lygIwVpkg9hplwEuXF2PgZIeVYw=/54x80/dkpu1ddg7pbsk.cloudfront.net/movie/11/22/60/11226026_ori.jpg",
        "profile": "http://resizing.flixster.com/lygIwVpkg9hplwEuXF2PgZIeVYw=/54x80/dkpu1ddg7pbsk.cloudfront.net/movie/11/22/60/11226026_ori.jpg",
        "detailed": "http://resizing.flixster.com/lygIwVpkg9hplwEuXF2PgZIeVYw=/54x80/dkpu1ddg7pbsk.cloudfront.net/movie/11/22/60/11226026_ori.jpg",
        "original": "http://resizing.flixster.com/lygIwVpkg9hplwEuXF2PgZIeVYw=/54x80/dkpu1ddg7pbsk.cloudfront.net/movie/11/22/60/11226026_ori.jpg"
      },
      "abridged_cast": [
        {
          "name": "Michael B. Jordan",
          "id": "770683889",
          "characters": [
            "Adonis Johnson"
          ]
        },
        {
          "name": "Sylvester Stallone",
          "id": "162664630",
          "characters": [
            "Rocky Balboa"
          ]
        },
        {
          "name": "Tessa Thompson",
          "id": "364606996",
          "characters": [
            "Bianca"
          ]
        },
        {
          "name": "Phylicia Rashad",
          "id": "162672874",
          "characters": [
            "Mary Anne Creed"
          ]
        },
        {
          "name": "Anthony Bellew",
          "id": "771653678",
          "characters": [
            "\"Pretty\" Ricky Conlan"
          ]
        }
      ],
      "links": {
        "self": "http://api.rottentomatoes.com/api/public/v1.0/movies/771413507.json",
        "alternate": "http://www.rottentomatoes.com/m/creed_2015/",
        "cast": "http://api.rottentomatoes.com/api/public/v1.0/movies/771413507/cast.json",
        "reviews": "http://api.rottentomatoes.com/api/public/v1.0/movies/771413507/reviews.json",
        "similar": "http://api.rottentomatoes.com/api/public/v1.0/movies/771413507/similar.json"
      }
    },
    {
      "id": "771379474",
      "title": "The Night Before",
      "year": 2015,
      "mpaa_rating": "R",
      "runtime": 101,
      "critics_consensus": "",
      "release_dates": {
        "theater": "2015-11-20"
      },
      "ratings": {
        "critics_rating": "Fresh",
        "critics_score": 64,
        "audience_rating": "Upright",
        "audience_score": 74
      },
      "synopsis": "Ethan (Joseph Gordon-Levitt), Isaac (Seth Rogen) and Chris (Anthony Mackie) have been friends since childhood, and for a decade, their yearly Christmas Eve reunion has been an annual night of debauchery and hilarity. Now that they're entering adulthood, the tradition is coming to an end, and to make it as memorable as possible, they set out to find the Nutcracka Ball - the Holy Grail of Christmas parties.",
      "posters": {
        "thumbnail": "http://resizing.flixster.com/SKlrZQtE7hxzpPt_sbMRPgNm6TU=/54x80/dkpu1ddg7pbsk.cloudfront.net/movie/11/19/17/11191775_ori.jpg",
        "profile": "http://resizing.flixster.com/SKlrZQtE7hxzpPt_sbMRPgNm6TU=/54x80/dkpu1ddg7pbsk.cloudfront.net/movie/11/19/17/11191775_ori.jpg",
        "detailed": "http://resizing.flixster.com/SKlrZQtE7hxzpPt_sbMRPgNm6TU=/54x80/dkpu1ddg7pbsk.cloudfront.net/movie/11/19/17/11191775_ori.jpg",
        "original": "http://resizing.flixster.com/SKlrZQtE7hxzpPt_sbMRPgNm6TU=/54x80/dkpu1ddg7pbsk.cloudfront.net/movie/11/19/17/11191775_ori.jpg"
      },
      "abridged_cast": [
        {
          "name": "Joseph Gordon-Levitt",
          "id": "162666960"
        },
        {
          "name": "Seth Rogen",
          "id": "162653310"
        },
        {
          "name": "Anthony Mackie",
          "id": "162653786"
        },
        {
          "name": "Lizzy Caplan",
          "id": "347990526",
          "characters": [
            "Diana"
          ]
        },
        {
          "name": "Michael Shannon",
          "id": "368451324"
        }
      ],
      "alternate_ids": {
        "imdb": "3530002"
      },
      "links": {
        "self": "http://api.rottentomatoes.com/api/public/v1.0/movies/771379474.json",
        "alternate": "http://www.rottentomatoes.com/m/the_night_before_2015/",
        "cast": "http://api.rottentomatoes.com/api/public/v1.0/movies/771379474/cast.json",
        "reviews": "http://api.rottentomatoes.com/api/public/v1.0/movies/771379474/reviews.json",
        "similar": "http://api.rottentomatoes.com/api/public/v1.0/movies/771379474/similar.json"
      }
    },
    {
      "id": "771360513",
      "title": "Spectre",
      "year": 2015,
      "mpaa_rating": "PG-13",
      "runtime": 150,
      "critics_consensus": "",
      "release_dates": {
        "theater": "2015-11-06"
      },
      "ratings": {
        "critics_rating": "Fresh",
        "critics_score": 64,
        "audience_rating": "Upright",
        "audience_score": 66
      },
      "synopsis": "A cryptic message from Bond's past sends him on a trail to uncover a sinister organisation. While M battles political forces to keep the secret service alive, Bond peels back the layers of deceit to reveal the terrible truth behind Spectre.",
      "posters": {
        "thumbnail": "http://resizing.flixster.com/52shS-7jfsIlzooulG4O021V1sQ=/54x80/dkpu1ddg7pbsk.cloudfront.net/movie/11/20/33/11203374_ori.jpg",
        "profile": "http://resizing.flixster.com/52shS-7jfsIlzooulG4O021V1sQ=/54x80/dkpu1ddg7pbsk.cloudfront.net/movie/11/20/33/11203374_ori.jpg",
        "detailed": "http://resizing.flixster.com/52shS-7jfsIlzooulG4O021V1sQ=/54x80/dkpu1ddg7pbsk.cloudfront.net/movie/11/20/33/11203374_ori.jpg",
        "original": "http://resizing.flixster.com/52shS-7jfsIlzooulG4O021V1sQ=/54x80/dkpu1ddg7pbsk.cloudfront.net/movie/11/20/33/11203374_ori.jpg"
      },
      "abridged_cast": [
        {
          "name": "Daniel Craig",
          "id": "162687443",
          "characters": [
            "James Bond"
          ]
        },
        {
          "name": "Christoph Waltz",
          "id": "770738334",
          "characters": [
            "Franz Oberhauser"
          ]
        },
        {
          "name": "Lea Seydoux",
          "id": "770811453",
          "characters": [
            "Madeleine Swann"
          ]
        },
        {
          "name": "Naomie Harris",
          "id": "162705781",
          "characters": [
            "Eve Moneypenney"
          ]
        },
        {
          "name": "Ben Whishaw",
          "id": "364605105",
          "characters": [
            "Q"
          ]
        }
      ],
      "alternate_ids": {
        "imdb": "2379713"
      },
      "links": {
        "self": "http://api.rottentomatoes.com/api/public/v1.0/movies/771360513.json",
        "alternate": "http://www.rottentomatoes.com/m/spectre_2015/",
        "cast": "http://api.rottentomatoes.com/api/public/v1.0/movies/771360513/cast.json",
        "reviews": "http://api.rottentomatoes.com/api/public/v1.0/movies/771360513/reviews.json",
        "similar": "http://api.rottentomatoes.com/api/public/v1.0/movies/771360513/similar.json"
      }
    },
    {
      "id": "771351525",
      "title": "Victor Frankenstein",
      "year": 2015,
      "mpaa_rating": "PG-13",
      "runtime": 109,
      "critics_consensus": "",
      "release_dates": {
        "theater": "2015-11-25"
      },
      "ratings": {
        "critics_rating": "Rotten",
        "critics_score": 26,
        "audience_rating": "Spilled",
        "audience_score": 48
      },
      "synopsis": "James McAvoy and Daniel Radcliffe star in a dynamic and thrilling twist on a legendary tale. Radical scientist Victor Frankenstein (McAvoy) and his equally brilliant protege Igor Strausman (Radcliffe) share a noble vision of aiding humanity through their groundbreaking research into immortality. But Victor's experiments go too far, and his obsession has horrifying consequences. Only Igor can bring his friend back from the brink of madness and save him from his monstrous creation. (C) Fox",
      "posters": {
        "thumbnail": "http://resizing.flixster.com/MI2aaGVn2Q5paT-sWU84PJGpJ3I=/54x81/dkpu1ddg7pbsk.cloudfront.net/movie/11/20/34/11203416_ori.jpg",
        "profile": "http://resizing.flixster.com/MI2aaGVn2Q5paT-sWU84PJGpJ3I=/54x81/dkpu1ddg7pbsk.cloudfront.net/movie/11/20/34/11203416_ori.jpg",
        "detailed": "http://resizing.flixster.com/MI2aaGVn2Q5paT-sWU84PJGpJ3I=/54x81/dkpu1ddg7pbsk.cloudfront.net/movie/11/20/34/11203416_ori.jpg",
        "original": "http://resizing.flixster.com/MI2aaGVn2Q5paT-sWU84PJGpJ3I=/54x81/dkpu1ddg7pbsk.cloudfront.net/movie/11/20/34/11203416_ori.jpg"
      },
      "abridged_cast": [
        {
          "name": "James McAvoy",
          "id": "162714854",
          "characters": [
            "Victor Frankenstein"
          ]
        },
        {
          "name": "Daniel Radcliffe",
          "id": "162655375",
          "characters": [
            "Igor"
          ]
        },
        {
          "name": "Jessica Brown Findlay",
          "id": "771479155",
          "characters": [
            "Lorelei"
          ]
        },
        {
          "name": "Andrew Scott",
          "id": "586476044",
          "characters": [
            "Roderick Turpin"
          ]
        },
        {
          "name": "Mark Gatiss",
          "id": "770745672",
          "characters": [
            "Dettweiler"
          ]
        }
      ],
      "alternate_ids": {
        "imdb": "1976009"
      },
      "links": {
        "self": "http://api.rottentomatoes.com/api/public/v1.0/movies/771351525.json",
        "alternate": "http://www.rottentomatoes.com/m/victor_frankenstein_2015/",
        "cast": "http://api.rottentomatoes.com/api/public/v1.0/movies/771351525/cast.json",
        "reviews": "http://api.rottentomatoes.com/api/public/v1.0/movies/771351525/reviews.json",
        "similar": "http://api.rottentomatoes.com/api/public/v1.0/movies/771351525/similar.json"
      }
    },
    {
      "id": "771414378",
      "title": "Secret in Their Eyes",
      "year": 2015,
      "mpaa_rating": "PG-13",
      "runtime": 111,
      "critics_consensus": "",
      "release_dates": {
        "theater": "2015-11-20"
      },
      "ratings": {
        "critics_rating": "Rotten",
        "critics_score": 40,
        "audience_rating": "Spilled",
        "audience_score": 47
      },
      "synopsis": "A tight-knit team of rising investigators - Ray (Chiwetel Ejiofor) and Jess (Julia Roberts), along with their supervisor Claire (Nicole Kidman) - is suddenly torn apart when they discover that Jess's teenage daughter has been brutally and inexplicably murdered. Now, thirteen years later, after obsessively searching every day for the elusive killer, Ray finally uncovers a new lead that he's certain can permanently resolve the case, nail the vicious murderer, and bring long-desired closure to his team. No one is prepared, however, for the shocking, unspeakable secret that will reveal the enduring, destructive effects of personal vengeance on the human soul.",
      "posters": {
        "thumbnail": "http://resizing.flixster.com/Q2zy0Hx6s22TbyuJ7RqxJLz8-HI=/54x80/dkpu1ddg7pbsk.cloudfront.net/movie/11/20/30/11203038_ori.jpg",
        "profile": "http://resizing.flixster.com/Q2zy0Hx6s22TbyuJ7RqxJLz8-HI=/54x80/dkpu1ddg7pbsk.cloudfront.net/movie/11/20/30/11203038_ori.jpg",
        "detailed": "http://resizing.flixster.com/Q2zy0Hx6s22TbyuJ7RqxJLz8-HI=/54x80/dkpu1ddg7pbsk.cloudfront.net/movie/11/20/30/11203038_ori.jpg",
        "original": "http://resizing.flixster.com/Q2zy0Hx6s22TbyuJ7RqxJLz8-HI=/54x80/dkpu1ddg7pbsk.cloudfront.net/movie/11/20/30/11203038_ori.jpg"
      },
      "abridged_cast": [
        {
          "name": "Chiwetel Ejiofor",
          "id": "162654272",
          "characters": [
            "Ray"
          ]
        },
        {
          "name": "Julia Roberts",
          "id": "162659460",
          "characters": [
            "Jess"
          ]
        },
        {
          "name": "Nicole Kidman",
          "id": "162652279",
          "characters": [
            "Claire"
          ]
        },
        {
          "name": "Dean Norris",
          "id": "770671539",
          "characters": [
            "Bumpy"
          ]
        },
        {
          "name": "Alfred Molina",
          "id": "162659152",
          "characters": [
            "Martin Morales"
          ]
        }
      ],
      "links": {
        "self": "http://api.rottentomatoes.com/api/public/v1.0/movies/771414378.json",
        "alternate": "http://www.rottentomatoes.com/m/secret_in_their_eyes_2015/",
        "cast": "http://api.rottentomatoes.com/api/public/v1.0/movies/771414378/cast.json",
        "reviews": "http://api.rottentomatoes.com/api/public/v1.0/movies/771414378/reviews.json",
        "similar": "http://api.rottentomatoes.com/api/public/v1.0/movies/771414378/similar.json"
      }
    },
    {
      "id": "771415822",
      "title": "Love the Coopers",
      "year": 2015,
      "mpaa_rating": "PG-13",
      "runtime": 120,
      "critics_consensus": "",
      "release_dates": {
        "theater": "2015-11-13"
      },
      "ratings": {
        "critics_rating": "Rotten",
        "critics_score": 22,
        "audience_rating": "Spilled",
        "audience_score": 41
      },
      "synopsis": "LOVE THE COOPERS follows the Cooper clan as four generations of extended family come together for their annual Christmas Eve celebration. As the evening unfolds, a series of unexpected visitors and unlikely events turn the night upside down, leading them all toward a surprising rediscovery of family bonds and the spirit of the holiday.",
      "posters": {
        "thumbnail": "http://resizing.flixster.com/7ofnfIBezQT6Na3CZGa5pUTRomY=/54x80/dkpu1ddg7pbsk.cloudfront.net/movie/11/20/31/11203175_ori.jpg",
        "profile": "http://resizing.flixster.com/7ofnfIBezQT6Na3CZGa5pUTRomY=/54x80/dkpu1ddg7pbsk.cloudfront.net/movie/11/20/31/11203175_ori.jpg",
        "detailed": "http://resizing.flixster.com/7ofnfIBezQT6Na3CZGa5pUTRomY=/54x80/dkpu1ddg7pbsk.cloudfront.net/movie/11/20/31/11203175_ori.jpg",
        "original": "http://resizing.flixster.com/7ofnfIBezQT6Na3CZGa5pUTRomY=/54x80/dkpu1ddg7pbsk.cloudfront.net/movie/11/20/31/11203175_ori.jpg"
      },
      "abridged_cast": [
        {
          "name": "Alan Arkin",
          "id": "162666144",
          "characters": [
            "Bucky"
          ]
        },
        {
          "name": "John Goodman",
          "id": "162655706",
          "characters": [
            "Sam"
          ]
        },
        {
          "name": "Ed Helms",
          "id": "770691762",
          "characters": [
            "Hank"
          ]
        },
        {
          "name": "Diane Keaton",
          "id": "162660369",
          "characters": [
            "Charlotte"
          ]
        },
        {
          "name": "Jake Lacy",
          "id": "771454620",
          "characters": [
            "Joe"
          ]
        }
      ],
      "links": {
        "self": "http://api.rottentomatoes.com/api/public/v1.0/movies/771415822.json",
        "alternate": "http://www.rottentomatoes.com/m/love_the_coopers/",
        "cast": "http://api.rottentomatoes.com/api/public/v1.0/movies/771415822/cast.json",
        "reviews": "http://api.rottentomatoes.com/api/public/v1.0/movies/771415822/reviews.json",
        "similar": "http://api.rottentomatoes.com/api/public/v1.0/movies/771415822/similar.json"
      }
    },
    {
      "id": "771380589",
      "title": "The Martian",
      "year": 2015,
      "mpaa_rating": "PG-13",
      "runtime": 134,
      "critics_consensus": "",
      "release_dates": {
        "theater": "2015-10-02"
      },
      "ratings": {
        "critics_rating": "Certified Fresh",
        "critics_score": 93,
        "audience_rating": "Upright",
        "audience_score": 93
      },
      "synopsis": "During a manned mission to Mars, Astronaut Mark Watney (Matt Damon) is presumed dead after a fierce storm and left behind by his crew. But Watney has survived and finds himself stranded and alone on the hostile planet. With only meager supplies, he must draw upon his ingenuity, wit and spirit to subsist and find a way to signal to Earth that he is alive. Millions of miles away, NASA and a team of international scientists work tirelessly to bring \"the Martian\" home, while his crewmates concurrently plot a daring, if not impossible rescue mission. As these stories of incredible bravery unfold, the world comes together to root for Watney's safe return. Based on a best-selling novel, and helmed by master director Ridley Scott, THE MARTIAN features a star studded cast that includes Jessica Chastain, Kristen Wiig, Kate Mara, Michael Pena, Jeff Daniels, Chiwetel Ejiofor, and Donald Glover. (C) Fox",
      "posters": {
        "thumbnail": "http://resizing.flixster.com/w1m455J_AaUzi_Aaca2vpL2VymI=/54x80/dkpu1ddg7pbsk.cloudfront.net/movie/11/20/23/11202355_ori.jpg",
        "profile": "http://resizing.flixster.com/w1m455J_AaUzi_Aaca2vpL2VymI=/54x80/dkpu1ddg7pbsk.cloudfront.net/movie/11/20/23/11202355_ori.jpg",
        "detailed": "http://resizing.flixster.com/w1m455J_AaUzi_Aaca2vpL2VymI=/54x80/dkpu1ddg7pbsk.cloudfront.net/movie/11/20/23/11202355_ori.jpg",
        "original": "http://resizing.flixster.com/w1m455J_AaUzi_Aaca2vpL2VymI=/54x80/dkpu1ddg7pbsk.cloudfront.net/movie/11/20/23/11202355_ori.jpg"
      },
      "abridged_cast": [
        {
          "name": "Matt Damon",
          "id": "162653499",
          "characters": [
            "Mark Watney"
          ]
        },
        {
          "name": "Jessica Chastain",
          "id": "770760183",
          "characters": [
            "Melissa Lewis"
          ]
        },
        {
          "name": "Kristen Wiig",
          "id": "770670481",
          "characters": [
            "Annie Montrose"
          ]
        },
        {
          "name": "Jeff Daniels",
          "id": "162654392",
          "characters": [
            "Teddy Sanders"
          ]
        },
        {
          "name": "Michael Pena",
          "id": "309887156",
          "characters": [
            "Rick Martinez"
          ]
        }
      ],
      "alternate_ids": {
        "imdb": "3659388"
      },
      "links": {
        "self": "http://api.rottentomatoes.com/api/public/v1.0/movies/771380589.json",
        "alternate": "http://www.rottentomatoes.com/m/the_martian/",
        "cast": "http://api.rottentomatoes.com/api/public/v1.0/movies/771380589/cast.json",
        "reviews": "http://api.rottentomatoes.com/api/public/v1.0/movies/771380589/reviews.json",
        "similar": "http://api.rottentomatoes.com/api/public/v1.0/movies/771380589/similar.json"
      }
    },
    {
      "id": "771370504",
      "title": "Brooklyn",
      "year": 2015,
      "mpaa_rating": "PG-13",
      "runtime": 111,
      "critics_consensus": "",
      "release_dates": {
        "theater": "2015-11-04"
      },
      "ratings": {
        "critics_rating": "Certified Fresh",
        "critics_score": 99,
        "audience_rating": "Upright",
        "audience_score": 93
      },
      "synopsis": "BROOKLYN tells the profoundly moving story of Eilis Lacey (Saoirse Ronan), a young Irish immigrant navigating her way through 1950s Brooklyn. Lured by the promise of America, Eilis departs Ireland and the comfort of her mother's home for the shores of New York City. The initial shackles of homesickness quickly diminish as a fresh romance sweeps Eilis into the intoxicating charm of love. But soon, her new vivacity is disrupted by her past, and Eilis must choose between two countries and the lives that exist within. (C) Fox Searchlight",
      "posters": {
        "thumbnail": "http://resizing.flixster.com/k28wtu-suNnah-2fJLUd9Kc_sc0=/54x80/dkpu1ddg7pbsk.cloudfront.net/movie/11/20/19/11201971_ori.jpg",
        "profile": "http://resizing.flixster.com/k28wtu-suNnah-2fJLUd9Kc_sc0=/54x80/dkpu1ddg7pbsk.cloudfront.net/movie/11/20/19/11201971_ori.jpg",
        "detailed": "http://resizing.flixster.com/k28wtu-suNnah-2fJLUd9Kc_sc0=/54x80/dkpu1ddg7pbsk.cloudfront.net/movie/11/20/19/11201971_ori.jpg",
        "original": "http://resizing.flixster.com/k28wtu-suNnah-2fJLUd9Kc_sc0=/54x80/dkpu1ddg7pbsk.cloudfront.net/movie/11/20/19/11201971_ori.jpg"
      },
      "abridged_cast": [
        {
          "name": "Saoirse Ronan",
          "id": "770680691"
        },
        {
          "name": "Domhnall Gleeson",
          "id": "770702167"
        },
        {
          "name": "Emory Cohen",
          "id": "770813996"
        },
        {
          "name": "Eileen O'Higgins",
          "id": "771073728",
          "characters": [
            "Nancy"
          ]
        },
        {
          "name": "Julie Walters",
          "id": "162662872",
          "characters": [
            "Mrs. Kehoe"
          ]
        }
      ],
      "alternate_ids": {
        "imdb": "2381111"
      },
      "links": {
        "self": "http://api.rottentomatoes.com/api/public/v1.0/movies/771370504.json",
        "alternate": "http://www.rottentomatoes.com/m/brooklyn/",
        "cast": "http://api.rottentomatoes.com/api/public/v1.0/movies/771370504/cast.json",
        "reviews": "http://api.rottentomatoes.com/api/public/v1.0/movies/771370504/reviews.json",
        "similar": "http://api.rottentomatoes.com/api/public/v1.0/movies/771370504/similar.json"
      }
    },
    {
      "id": "771420359",
      "title": "Spotlight",
      "year": 2015,
      "mpaa_rating": "R",
      "runtime": 127,
      "critics_consensus": "",
      "release_dates": {
        "theater": "2015-11-06"
      },
      "ratings": {
        "critics_rating": "Certified Fresh",
        "critics_score": 98,
        "audience_rating": "Upright",
        "audience_score": 97
      },
      "synopsis": "SPOTLIGHT tells the riveting true story of the Pulitzer Prize-winning Boston Globe investigation that would rock the city and cause a crisis in one of the world's oldest and most trusted institutions. When the newspaper's tenacious \"Spotlight\" team of reporters delves into allegations of abuse in the Catholic Church, their year-long investigation uncovers a decades-long cover-up at the highest levels of Boston's religious, legal, and government establishment, touching off a wave of revelations around the world. Directed by Academy Award-nominee Tom McCarthy, SPOTLIGHT is a tense investigative dramatic-thriller, tracing the steps to one of the biggest cover-ups in modern times. (C) Open Road",
      "posters": {
        "thumbnail": "http://resizing.flixster.com/9QwldYplyjEBxs7q3oHpxnHMyZY=/54x80/dkpu1ddg7pbsk.cloudfront.net/movie/11/20/15/11201558_ori.jpg",
        "profile": "http://resizing.flixster.com/9QwldYplyjEBxs7q3oHpxnHMyZY=/54x80/dkpu1ddg7pbsk.cloudfront.net/movie/11/20/15/11201558_ori.jpg",
        "detailed": "http://resizing.flixster.com/9QwldYplyjEBxs7q3oHpxnHMyZY=/54x80/dkpu1ddg7pbsk.cloudfront.net/movie/11/20/15/11201558_ori.jpg",
        "original": "http://resizing.flixster.com/9QwldYplyjEBxs7q3oHpxnHMyZY=/54x80/dkpu1ddg7pbsk.cloudfront.net/movie/11/20/15/11201558_ori.jpg"
      },
      "abridged_cast": [
        {
          "name": "Mark Ruffalo",
          "id": "162653904",
          "characters": [
            "Michael Rezendes"
          ]
        },
        {
          "name": "Michael Keaton",
          "id": "162652681",
          "characters": [
            "Walter \"Robby\" Robinson"
          ]
        },
        {
          "name": "Rachel McAdams",
          "id": "162652838",
          "characters": [
            "Sacha Pfeiffer"
          ]
        },
        {
          "name": "Stanley Tucci",
          "id": "162661152",
          "characters": [
            "Mitchell Garabedian"
          ]
        },
        {
          "name": "Liev Schreiber",
          "id": "162653994",
          "characters": [
            "Marty Baron"
          ]
        }
      ],
      "alternate_ids": {
        "imdb": "1895587"
      },
      "links": {
        "self": "http://api.rottentomatoes.com/api/public/v1.0/movies/771420359.json",
        "alternate": "http://www.rottentomatoes.com/m/spotlight_2015/",
        "cast": "http://api.rottentomatoes.com/api/public/v1.0/movies/771420359/cast.json",
        "reviews": "http://api.rottentomatoes.com/api/public/v1.0/movies/771420359/reviews.json",
        "similar": "http://api.rottentomatoes.com/api/public/v1.0/movies/771420359/similar.json"
      }
    },
    {
      "id": "771359098",
      "title": "The 33",
      "year": 2015,
      "mpaa_rating": "PG-13",
      "runtime": 120,
      "critics_consensus": "",
      "release_dates": {
        "theater": "2015-11-13"
      },
      "ratings": {
        "critics_rating": "Rotten",
        "critics_score": 42,
        "audience_rating": "Upright",
        "audience_score": 65
      },
      "synopsis": "The true story of the 2010 collapse of a Chilean mine and the rescue of the 33 miners who were trapped underground for 69 days.",
      "posters": {
        "thumbnail": "http://resizing.flixster.com/Tiu7P0k3eWPeDZ6gjaSoYQFvXME=/54x80/dkpu1ddg7pbsk.cloudfront.net/movie/11/19/18/11191884_ori.jpg",
        "profile": "http://resizing.flixster.com/Tiu7P0k3eWPeDZ6gjaSoYQFvXME=/54x80/dkpu1ddg7pbsk.cloudfront.net/movie/11/19/18/11191884_ori.jpg",
        "detailed": "http://resizing.flixster.com/Tiu7P0k3eWPeDZ6gjaSoYQFvXME=/54x80/dkpu1ddg7pbsk.cloudfront.net/movie/11/19/18/11191884_ori.jpg",
        "original": "http://resizing.flixster.com/Tiu7P0k3eWPeDZ6gjaSoYQFvXME=/54x80/dkpu1ddg7pbsk.cloudfront.net/movie/11/19/18/11191884_ori.jpg"
      },
      "abridged_cast": [
        {
          "name": "Antonio Banderas",
          "id": "162654885",
          "characters": [
            "Mario Sepulveda"
          ]
        },
        {
          "name": "Rodrigo Santoro",
          "id": "162676528",
          "characters": [
            "Laurence Golborne"
          ]
        },
        {
          "name": "James Brolin",
          "id": "162670952",
          "characters": [
            "Jeff Hart"
          ]
        },
        {
          "name": "Juliette Binoche",
          "id": "162655186",
          "characters": [
            "Maria Segovia"
          ]
        },
        {
          "name": "Cote de Pablo",
          "id": "770788717",
          "characters": [
            "Jessica Salgado"
          ]
        }
      ],
      "alternate_ids": {
        "imdb": "2006295"
      },
      "links": {
        "self": "http://api.rottentomatoes.com/api/public/v1.0/movies/771359098.json",
        "alternate": "http://www.rottentomatoes.com/m/the_33/",
        "cast": "http://api.rottentomatoes.com/api/public/v1.0/movies/771359098/cast.json",
        "reviews": "http://api.rottentomatoes.com/api/public/v1.0/movies/771359098/reviews.json",
        "similar": "http://api.rottentomatoes.com/api/public/v1.0/movies/771359098/similar.json"
      }
    },
    {
      "id": "771415583",
      "title": "Trumbo",
      "year": 2015,
      "mpaa_rating": "R",
      "runtime": 124,
      "critics_consensus": "",
      "release_dates": {
        "theater": "2015-11-06"
      },
      "ratings": {
        "critics_rating": "Fresh",
        "critics_score": 71,
        "audience_rating": "Upright",
        "audience_score": 82
      },
      "synopsis": "In 1947, Dalton Trumbo (Bryan Cranston) was Hollywood's top screenwriter until he and other artists were jailed and blacklisted for their political beliefs. TRUMBO (directed by Jay Roach) recounts how Dalton used words and wit to win two Academy Awards and expose the absurdity and injustice of the blacklist, which entangled everyone from gossip columnist Hedda Hopper (Helen Mirren) to John Wayne, Kirk Douglas and Otto Preminger.",
      "posters": {
        "thumbnail": "http://resizing.flixster.com/MnAvic7MjQr527o5Wx2e-aJTDyA=/54x80/dkpu1ddg7pbsk.cloudfront.net/movie/11/19/18/11191857_ori.jpg",
        "profile": "http://resizing.flixster.com/MnAvic7MjQr527o5Wx2e-aJTDyA=/54x80/dkpu1ddg7pbsk.cloudfront.net/movie/11/19/18/11191857_ori.jpg",
        "detailed": "http://resizing.flixster.com/MnAvic7MjQr527o5Wx2e-aJTDyA=/54x80/dkpu1ddg7pbsk.cloudfront.net/movie/11/19/18/11191857_ori.jpg",
        "original": "http://resizing.flixster.com/MnAvic7MjQr527o5Wx2e-aJTDyA=/54x80/dkpu1ddg7pbsk.cloudfront.net/movie/11/19/18/11191857_ori.jpg"
      },
      "abridged_cast": [
        {
          "name": "Bryan Cranston",
          "id": "326392501",
          "characters": [
            "Dalton Trumbo"
          ]
        },
        {
          "name": "Alan Tudyk",
          "id": "162654268",
          "characters": [
            "Ian McLellan Hunter"
          ]
        },
        {
          "name": "Diane Lane",
          "id": "162652926",
          "characters": [
            "Cleo Trumbo"
          ]
        },
        {
          "name": "Elle Fanning",
          "id": "528361349",
          "characters": [
            "Nikola Trumbo"
          ]
        },
        {
          "name": "Helen Mirren",
          "id": "162662871",
          "characters": [
            "Hedda Hopper"
          ]
        }
      ],
      "links": {
        "self": "http://api.rottentomatoes.com/api/public/v1.0/movies/771415583.json",
        "alternate": "http://www.rottentomatoes.com/m/trumbo/",
        "cast": "http://api.rottentomatoes.com/api/public/v1.0/movies/771415583/cast.json",
        "reviews": "http://api.rottentomatoes.com/api/public/v1.0/movies/771415583/reviews.json",
        "similar": "http://api.rottentomatoes.com/api/public/v1.0/movies/771415583/similar.json"
      }
    },
    {
      "id": "770807799",
      "title": "Goosebumps",
      "year": 2015,
      "mpaa_rating": "PG",
      "runtime": 103,
      "critics_consensus": "",
      "release_dates": {
        "theater": "2015-10-16"
      },
      "ratings": {
        "critics_rating": "Fresh",
        "critics_score": 74,
        "audience_rating": "Upright",
        "audience_score": 73
      },
      "synopsis": "Upset about moving from a big city to a small town, teenager Zach Cooper (Dylan Minnette) finds a silver lining when he meets the beautiful girl, Hannah (Odeya Rush), living right next door. But every silver lining has a cloud, and Zach's comes when he learns that Hannah has a mysterious dad who is revealed to be R. L. Stine (Jack Black), the author of the bestselling Goosebumps series. It turns out that there is a reason why Stine is so strange... he is a prisoner of his own imagination - the monsters that his books made famous are real, and Stine protects his readers by keeping them locked up in their books. When Zach unintentionally unleashes the monsters from their manuscripts and they begin to terrorize the town, it's suddenly up to Stine, Zach, and Hannah to get all of them back in the books where they belong. Note: Scholastic has sold over 400 million Goosebumps books worldwide in 32 languages since the series introduction in 1992, earning critical acclaim and dominating global best seller lists. R.L. Stine has been recognized as one of the bestselling children's authors in history. (c) Sony",
      "posters": {
        "thumbnail": "http://resizing.flixster.com/s6Z8WRS8z94QTJil3axVPx3NFoM=/54x72/dkpu1ddg7pbsk.cloudfront.net/movie/11/19/31/11193185_ori.jpg",
        "profile": "http://resizing.flixster.com/s6Z8WRS8z94QTJil3axVPx3NFoM=/54x72/dkpu1ddg7pbsk.cloudfront.net/movie/11/19/31/11193185_ori.jpg",
        "detailed": "http://resizing.flixster.com/s6Z8WRS8z94QTJil3axVPx3NFoM=/54x72/dkpu1ddg7pbsk.cloudfront.net/movie/11/19/31/11193185_ori.jpg",
        "original": "http://resizing.flixster.com/s6Z8WRS8z94QTJil3axVPx3NFoM=/54x72/dkpu1ddg7pbsk.cloudfront.net/movie/11/19/31/11193185_ori.jpg"
      },
      "abridged_cast": [
        {
          "name": "Jack Black",
          "id": "162662218",
          "characters": [
            "R.L. Stine"
          ]
        },
        {
          "name": "Dylan Minnette",
          "id": "770808601",
          "characters": [
            "Zach Cooper"
          ]
        },
        {
          "name": "Odeya Rush",
          "id": "771377595",
          "characters": [
            "Hannah"
          ]
        },
        {
          "name": "Amy Ryan",
          "id": "162653858",
          "characters": [
            "Gale"
          ]
        },
        {
          "name": "Jillian Bell",
          "id": "771103724",
          "characters": [
            "Lorraine"
          ]
        }
      ],
      "alternate_ids": {
        "imdb": "1051904"
      },
      "links": {
        "self": "http://api.rottentomatoes.com/api/public/v1.0/movies/770807799.json",
        "alternate": "http://www.rottentomatoes.com/m/goosebumps_2015/",
        "cast": "http://api.rottentomatoes.com/api/public/v1.0/movies/770807799/cast.json",
        "reviews": "http://api.rottentomatoes.com/api/public/v1.0/movies/770807799/reviews.json",
        "similar": "http://api.rottentomatoes.com/api/public/v1.0/movies/770807799/similar.json"
      }
    },
    {
      "id": "771379326",
      "title": "Bridge of Spies",
      "year": 2015,
      "mpaa_rating": "PG-13",
      "runtime": 135,
      "critics_consensus": "",
      "release_dates": {
        "theater": "2015-10-16"
      },
      "ratings": {
        "critics_rating": "Certified Fresh",
        "critics_score": 91,
        "audience_rating": "Upright",
        "audience_score": 90
      },
      "synopsis": "Tom Hanks stars as the American attorney tasked with negotiating the release of a U-2 spy plane pilot who was shot down over Russia at the height of the Cold War in this historical drama from DreamWorks Studios. Steven Spielberg and Mark E. Platt produce a film written by Matt Charman. ~ Jason Buchanan, Rovi",
      "posters": {
        "thumbnail": "http://resizing.flixster.com/E8nZbLv9ocwxiM7Ep2-QA3y8Y8A=/54x80/dkpu1ddg7pbsk.cloudfront.net/movie/11/19/14/11191456_ori.jpg",
        "profile": "http://resizing.flixster.com/E8nZbLv9ocwxiM7Ep2-QA3y8Y8A=/54x80/dkpu1ddg7pbsk.cloudfront.net/movie/11/19/14/11191456_ori.jpg",
        "detailed": "http://resizing.flixster.com/E8nZbLv9ocwxiM7Ep2-QA3y8Y8A=/54x80/dkpu1ddg7pbsk.cloudfront.net/movie/11/19/14/11191456_ori.jpg",
        "original": "http://resizing.flixster.com/E8nZbLv9ocwxiM7Ep2-QA3y8Y8A=/54x80/dkpu1ddg7pbsk.cloudfront.net/movie/11/19/14/11191456_ori.jpg"
      },
      "abridged_cast": [
        {
          "name": "Tom Hanks",
          "id": "162655641",
          "characters": [
            "James Donovan"
          ]
        },
        {
          "name": "Mark Rylance",
          "id": "162708436",
          "characters": [
            "Rudolf Abel"
          ]
        },
        {
          "name": "Noah Schnapp",
          "id": "771656761"
        },
        {
          "name": "John Scott Shepherd",
          "id": "770897269",
          "characters": [
            "Hoffman"
          ]
        },
        {
          "name": "Amy Ryan",
          "id": "162653858",
          "characters": [
            "Mary"
          ]
        }
      ],
      "alternate_ids": {
        "imdb": "3682448"
      },
      "links": {
        "self": "http://api.rottentomatoes.com/api/public/v1.0/movies/771379326.json",
        "alternate": "http://www.rottentomatoes.com/m/bridge_of_spies/",
        "cast": "http://api.rottentomatoes.com/api/public/v1.0/movies/771379326/cast.json",
        "reviews": "http://api.rottentomatoes.com/api/public/v1.0/movies/771379326/reviews.json",
        "similar": "http://api.rottentomatoes.com/api/public/v1.0/movies/771379326/similar.json"
      }
    },
    {
      "id": "771321495",
      "title": "Hotel Transylvania 2",
      "year": 2015,
      "mpaa_rating": "PG",
      "runtime": 89,
      "critics_consensus": "",
      "release_dates": {
        "theater": "2015-09-25",
        "dvd": "2016-01-12"
      },
      "ratings": {
        "critics_rating": "Rotten",
        "critics_score": 52,
        "audience_rating": "Upright",
        "audience_score": 70
      },
      "synopsis": "The hit CG-animated family comedy Hotel Transylvania gets a follow-up with this Sony Pictures Animation production.",
      "posters": {
        "thumbnail": "http://resizing.flixster.com/n_uO9xcTc6ZQWIkF5LbNfC1P4EA=/54x80/dkpu1ddg7pbsk.cloudfront.net/movie/11/19/15/11191564_ori.jpg",
        "profile": "http://resizing.flixster.com/n_uO9xcTc6ZQWIkF5LbNfC1P4EA=/54x80/dkpu1ddg7pbsk.cloudfront.net/movie/11/19/15/11191564_ori.jpg",
        "detailed": "http://resizing.flixster.com/n_uO9xcTc6ZQWIkF5LbNfC1P4EA=/54x80/dkpu1ddg7pbsk.cloudfront.net/movie/11/19/15/11191564_ori.jpg",
        "original": "http://resizing.flixster.com/n_uO9xcTc6ZQWIkF5LbNfC1P4EA=/54x80/dkpu1ddg7pbsk.cloudfront.net/movie/11/19/15/11191564_ori.jpg"
      },
      "abridged_cast": [
        {
          "name": "Selena Gomez",
          "id": "770686131",
          "characters": [
            "Mavis"
          ]
        },
        {
          "name": "Mel Brooks",
          "id": "162658738",
          "characters": [
            "Vlad"
          ]
        },
        {
          "name": "Kevin James",
          "id": "326298578",
          "characters": [
            "Frankenstein"
          ]
        },
        {
          "name": "Steve Buscemi",
          "id": "162652875",
          "characters": [
            "Wayne"
          ]
        },
        {
          "name": "Andy Samberg",
          "id": "602828424",
          "characters": [
            "Jonathan"
          ]
        }
      ],
      "alternate_ids": {
        "imdb": "2510894"
      },
      "links": {
        "self": "http://api.rottentomatoes.com/api/public/v1.0/movies/771321495.json",
        "alternate": "http://www.rottentomatoes.com/m/hotel_transylvania_2/",
        "cast": "http://api.rottentomatoes.com/api/public/v1.0/movies/771321495/cast.json",
        "reviews": "http://api.rottentomatoes.com/api/public/v1.0/movies/771321495/reviews.json",
        "similar": "http://api.rottentomatoes.com/api/public/v1.0/movies/771321495/similar.json"
      }
    },
    {
      "id": "771371532",
      "title": "Pan",
      "year": 2015,
      "mpaa_rating": "PG",
      "runtime": 111,
      "critics_consensus": "",
      "release_dates": {
        "theater": "2015-10-09"
      },
      "ratings": {
        "critics_rating": "Rotten",
        "critics_score": 26,
        "audience_rating": "Spilled",
        "audience_score": 49
      },
      "synopsis": "The story of an orphan who is spirited away to the magical Neverland. There, he finds both fun and dangers, and ultimately discovers his destiny -- to become the hero who will be forever known as Peter Pan.",
      "posters": {
        "thumbnail": "http://resizing.flixster.com/T6xspMTSa8ssZ4DJLjq8mG1JAI0=/54x80/dkpu1ddg7pbsk.cloudfront.net/movie/11/19/11/11191103_ori.jpg",
        "profile": "http://resizing.flixster.com/T6xspMTSa8ssZ4DJLjq8mG1JAI0=/54x80/dkpu1ddg7pbsk.cloudfront.net/movie/11/19/11/11191103_ori.jpg",
        "detailed": "http://resizing.flixster.com/T6xspMTSa8ssZ4DJLjq8mG1JAI0=/54x80/dkpu1ddg7pbsk.cloudfront.net/movie/11/19/11/11191103_ori.jpg",
        "original": "http://resizing.flixster.com/T6xspMTSa8ssZ4DJLjq8mG1JAI0=/54x80/dkpu1ddg7pbsk.cloudfront.net/movie/11/19/11/11191103_ori.jpg"
      },
      "abridged_cast": [
        {
          "name": "Levi Miller",
          "id": "771483902",
          "characters": [
            "Peter Pan"
          ]
        },
        {
          "name": "Hugh Jackman",
          "id": "162661503",
          "characters": [
            "Blackbeard"
          ]
        },
        {
          "name": "Rooney Mara",
          "id": "770826640",
          "characters": [
            "Tiger Lily"
          ]
        },
        {
          "name": "Amanda Seyfried",
          "id": "364614826",
          "characters": [
            "Mary"
          ]
        },
        {
          "name": "Garrett Hedlund",
          "id": "162653184",
          "characters": [
            "Hook"
          ]
        }
      ],
      "links": {
        "self": "http://api.rottentomatoes.com/api/public/v1.0/movies/771371532.json",
        "alternate": "http://www.rottentomatoes.com/m/pan_2015/",
        "cast": "http://api.rottentomatoes.com/api/public/v1.0/movies/771371532/cast.json",
        "reviews": "http://api.rottentomatoes.com/api/public/v1.0/movies/771371532/reviews.json",
        "similar": "http://api.rottentomatoes.com/api/public/v1.0/movies/771371532/similar.json"
      }
    },
    {
      "id": "771376303",
      "title": "Suffragette",
      "year": 2015,
      "mpaa_rating": "PG-13",
      "runtime": 106,
      "critics_consensus": "",
      "release_dates": {
        "theater": "2015-10-23"
      },
      "ratings": {
        "critics_rating": "Fresh",
        "critics_score": 72,
        "audience_rating": "Upright",
        "audience_score": 74
      },
      "synopsis": "Academy Award nominees Carey Mulligan and Helena Bonham Carter, and three-time Academy Award winner Meryl Streep, lead the cast of a powerful drama about the women who were willing to lose everything in their fight for equality in early-20th-century Britain. The stirring story centers on Maud (played by Carey Mulligan), a working wife and mother whose life is forever changed when she is secretly recruited to join the U.K.'s growing suffragette movement. Galvanized by the outlaw fugitive Emmeline Pankhurst (Meryl Streep), Maud becomes an activist for the cause alongside women from all walks of life. When increasingly aggressive police action forces Maud and her dedicated fellow suffragettes underground, they engage in a dangerous game of cat-and-mouse with the authorities, who are shocked as the women's civil disobedience escalates and sparks debate across the nation. Inspired by true events, SUFFRAGETTE is a moving drama exploring the passion and heartbreak of those who risked all they had for women's right to vote - their jobs, their homes, their children, and even their lives. The film also stars Ben Whishaw, Anne-Marie Duff, Brendan Gleeson, Romola Garai, and Natalie Press. SUFFRAGETTE is directed by BAFTA Award winner Sarah Gavron from an original screenplay by Emmy Award winner Abi Morgan. (C) Focus Features",
      "posters": {
        "thumbnail": "http://resizing.flixster.com/NW962st7d0SAlCAb3873N_KrYT8=/54x80/dkpu1ddg7pbsk.cloudfront.net/movie/11/20/16/11201612_ori.jpg",
        "profile": "http://resizing.flixster.com/NW962st7d0SAlCAb3873N_KrYT8=/54x80/dkpu1ddg7pbsk.cloudfront.net/movie/11/20/16/11201612_ori.jpg",
        "detailed": "http://resizing.flixster.com/NW962st7d0SAlCAb3873N_KrYT8=/54x80/dkpu1ddg7pbsk.cloudfront.net/movie/11/20/16/11201612_ori.jpg",
        "original": "http://resizing.flixster.com/NW962st7d0SAlCAb3873N_KrYT8=/54x80/dkpu1ddg7pbsk.cloudfront.net/movie/11/20/16/11201612_ori.jpg"
      },
      "abridged_cast": [
        {
          "name": "Carey Mulligan",
          "id": "770678627",
          "characters": [
            "Maud"
          ]
        },
        {
          "name": "Helena Bonham Carter",
          "id": "162652820",
          "characters": [
            "Edith New"
          ]
        },
        {
          "name": "Meryl Streep",
          "id": "162654900",
          "characters": [
            "Emmeline Pankhurst"
          ]
        },
        {
          "name": "Brendan Gleeson",
          "id": "162652243",
          "characters": [
            "Steed"
          ]
        },
        {
          "name": "Anne-Marie Duff",
          "id": "162694429",
          "characters": [
            "Violet Cambridge"
          ]
        }
      ],
      "alternate_ids": {
        "imdb": "3077214"
      },
      "links": {
        "self": "http://api.rottentomatoes.com/api/public/v1.0/movies/771376303.json",
        "alternate": "http://www.rottentomatoes.com/m/suffragette/",
        "cast": "http://api.rottentomatoes.com/api/public/v1.0/movies/771376303/cast.json",
        "reviews": "http://api.rottentomatoes.com/api/public/v1.0/movies/771376303/reviews.json",
        "similar": "http://api.rottentomatoes.com/api/public/v1.0/movies/771376303/similar.json"
      }
    },
    {
      "id": "771390260",
      "title": "Maze Runner: The Scorch Trials",
      "year": 2015,
      "mpaa_rating": "PG-13",
      "runtime": 129,
      "critics_consensus": "",
      "release_dates": {
        "theater": "2015-09-18"
      },
      "ratings": {
        "critics_rating": "Rotten",
        "critics_score": 49,
        "audience_rating": "Upright",
        "audience_score": 61
      },
      "synopsis": "In this next chapter of the epic \"Maze Runner\" saga, Thomas (Dylan O'Brien) and his fellow Gladers face their greatest challenge yet: searching for clues about the mysterious and powerful organization known as WCKD. Their journey takes them to the Scorch, a desolate landscape filled with unimaginable obstacles. Teaming up with resistance fighters, the Gladers take on WCKD's vastly superior forces and uncover its shocking plans for them all. (C) Fox",
      "posters": {
        "thumbnail": "http://resizing.flixster.com/ZV2A22qRMm64yWa2RcMTN3wED-8=/54x77/dkpu1ddg7pbsk.cloudfront.net/movie/11/19/13/11191378_ori.jpg",
        "profile": "http://resizing.flixster.com/ZV2A22qRMm64yWa2RcMTN3wED-8=/54x77/dkpu1ddg7pbsk.cloudfront.net/movie/11/19/13/11191378_ori.jpg",
        "detailed": "http://resizing.flixster.com/ZV2A22qRMm64yWa2RcMTN3wED-8=/54x77/dkpu1ddg7pbsk.cloudfront.net/movie/11/19/13/11191378_ori.jpg",
        "original": "http://resizing.flixster.com/ZV2A22qRMm64yWa2RcMTN3wED-8=/54x77/dkpu1ddg7pbsk.cloudfront.net/movie/11/19/13/11191378_ori.jpg"
      },
      "abridged_cast": [
        {
          "name": "Dylan O'Brien",
          "id": "771375271",
          "characters": [
            "Thomas"
          ]
        },
        {
          "name": "Thomas Sangster",
          "id": "162710614",
          "characters": [
            "Newt"
          ]
        },
        {
          "name": "Kaya Scodelario",
          "id": "770803276",
          "characters": [
            "Teresa"
          ]
        },
        {
          "name": "Aidan Gillen",
          "id": "364651634",
          "characters": [
            "Janson"
          ]
        },
        {
          "name": "Ki Hong Lee",
          "id": "771376026",
          "characters": [
            "Minho"
          ]
        }
      ],
      "alternate_ids": {
        "imdb": "4046784"
      },
      "links": {
        "self": "http://api.rottentomatoes.com/api/public/v1.0/movies/771390260.json",
        "alternate": "http://www.rottentomatoes.com/m/maze_runner_the_scorch_trials/",
        "cast": "http://api.rottentomatoes.com/api/public/v1.0/movies/771390260/cast.json",
        "reviews": "http://api.rottentomatoes.com/api/public/v1.0/movies/771390260/reviews.json",
        "similar": "http://api.rottentomatoes.com/api/public/v1.0/movies/771390260/similar.json"
      }
    },
    {
      "id": "771422480",
      "title": "Room",
      "year": 2015,
      "mpaa_rating": "R",
      "runtime": 113,
      "critics_consensus": "",
      "release_dates": {
        "theater": "2015-10-16"
      },
      "ratings": {
        "critics_rating": "Certified Fresh",
        "critics_score": 96,
        "audience_rating": "Upright",
        "audience_score": 94
      },
      "synopsis": "Both highly suspenseful and deeply emotional, ROOM is a unique and touching exploration of the boundless love between a mother and her child. After 5-year-old Jack (Jacob Tremblay) and his Ma (Brie Larson) escape from the enclosed surroundings that Jack has known his entire life, the boy makes a thrilling discovery: the outside world. As he experiences all the joy, excitement, and fear that this new adventure brings, he holds tight to the one thing that matters most of all--his special bond with his loving and devoted Ma.",
      "posters": {
        "thumbnail": "http://resizing.flixster.com/mi34ePp3MFXSW7dXVX7ypaHbvSs=/54x72/dkpu1ddg7pbsk.cloudfront.net/movie/11/20/02/11200274_ori.jpg",
        "profile": "http://resizing.flixster.com/mi34ePp3MFXSW7dXVX7ypaHbvSs=/54x72/dkpu1ddg7pbsk.cloudfront.net/movie/11/20/02/11200274_ori.jpg",
        "detailed": "http://resizing.flixster.com/mi34ePp3MFXSW7dXVX7ypaHbvSs=/54x72/dkpu1ddg7pbsk.cloudfront.net/movie/11/20/02/11200274_ori.jpg",
        "original": "http://resizing.flixster.com/mi34ePp3MFXSW7dXVX7ypaHbvSs=/54x72/dkpu1ddg7pbsk.cloudfront.net/movie/11/20/02/11200274_ori.jpg"
      },
      "abridged_cast": [
        {
          "name": "Brie Larson",
          "id": "341816562",
          "characters": [
            "Ma"
          ]
        },
        {
          "name": "Joan Allen",
          "id": "162660057",
          "characters": [
            "Grandma"
          ]
        },
        {
          "name": "William H. Macy",
          "id": "162652354",
          "characters": [
            "Grandpa"
          ]
        },
        {
          "name": "Jacob Tremblay",
          "id": "771451802",
          "characters": [
            "Jack"
          ]
        },
        {
          "name": "Tom McCamus",
          "id": "364598723",
          "characters": [
            "Leo"
          ]
        }
      ],
      "links": {
        "self": "http://api.rottentomatoes.com/api/public/v1.0/movies/771422480.json",
        "alternate": "http://www.rottentomatoes.com/m/room_2015/",
        "cast": "http://api.rottentomatoes.com/api/public/v1.0/movies/771422480/cast.json",
        "reviews": "http://api.rottentomatoes.com/api/public/v1.0/movies/771422480/reviews.json",
        "similar": "http://api.rottentomatoes.com/api/public/v1.0/movies/771422480/similar.json"
      }
    },
    {
      "id": "771427527",
      "title": "Tamasha",
      "year": 2015,
      "mpaa_rating": "Unrated",
      "runtime": "",
      "release_dates": {
        "theater": "2015-11-25"
      },
      "ratings": {
        "critics_score": -1,
        "audience_rating": "Upright",
        "audience_score": 69
      },
      "synopsis": "Tara, a young Indian girl finds herself stranded on the French island of Corsica after she loses all her possessions. In this time of distress, she meets Ved an Indian backpacker who extends to help her. To make their rendezvous more interesting and unpredictable they agree not to disclose their real identities to each other. For the next week, the two spend an indulgent time in Corsica having the time of their lives, until she finds a way to return back to India. Four years later, Tara finds Ved again. He is ordinary and lacking the charm that she remembered him for. Ultimately she rejects his proposal, sending Ved on a journey of self-discovery as he sets out to pursue Tara.",
      "posters": {
        "thumbnail": "http://resizing.flixster.com/hr5wi4sV5JWldeuASGMCfEF_Tdk=/54x77/dkpu1ddg7pbsk.cloudfront.net/movie/11/20/36/11203681_ori.jpg",
        "profile": "http://resizing.flixster.com/hr5wi4sV5JWldeuASGMCfEF_Tdk=/54x77/dkpu1ddg7pbsk.cloudfront.net/movie/11/20/36/11203681_ori.jpg",
        "detailed": "http://resizing.flixster.com/hr5wi4sV5JWldeuASGMCfEF_Tdk=/54x77/dkpu1ddg7pbsk.cloudfront.net/movie/11/20/36/11203681_ori.jpg",
        "original": "http://resizing.flixster.com/hr5wi4sV5JWldeuASGMCfEF_Tdk=/54x77/dkpu1ddg7pbsk.cloudfront.net/movie/11/20/36/11203681_ori.jpg"
      },
      "abridged_cast": [
        {
          "name": "Deepika Padukone",
          "id": "451735084"
        },
        {
          "name": "Ranbir Kapoor",
          "id": "770678460"
        },
        {
          "name": "Javed Sheikh",
          "id": "674531571"
        },
        {
          "name": "Nikhil Bhagat",
          "id": "770984954"
        },
        {
          "name": "Faraaz Servaia",
          "id": "771676329"
        }
      ],
      "links": {
        "self": "http://api.rottentomatoes.com/api/public/v1.0/movies/771427527.json",
        "alternate": "http://www.rottentomatoes.com/m/tamasha/",
        "cast": "http://api.rottentomatoes.com/api/public/v1.0/movies/771427527/cast.json",
        "reviews": "http://api.rottentomatoes.com/api/public/v1.0/movies/771427527/reviews.json",
        "similar": "http://api.rottentomatoes.com/api/public/v1.0/movies/771427527/similar.json"
      }
    },
    {
      "id": "771370466",
      "title": "The Intern",
      "year": 2015,
      "mpaa_rating": "PG-13",
      "runtime": 121,
      "critics_consensus": "",
      "release_dates": {
        "theater": "2015-09-25"
      },
      "ratings": {
        "critics_rating": "Fresh",
        "critics_score": 60,
        "audience_rating": "Upright",
        "audience_score": 78
      },
      "synopsis": "A retired successful business owner and widower lands an internship at a fashion website run by a young, career-driven woman. ~ Jason Buchanan, Rovi",
      "posters": {
        "thumbnail": "http://resizing.flixster.com/bvk3HvDiheSeXEVmSqZamTnuMs4=/54x80/dkpu1ddg7pbsk.cloudfront.net/movie/11/20/20/11202098_ori.jpg",
        "profile": "http://resizing.flixster.com/bvk3HvDiheSeXEVmSqZamTnuMs4=/54x80/dkpu1ddg7pbsk.cloudfront.net/movie/11/20/20/11202098_ori.jpg",
        "detailed": "http://resizing.flixster.com/bvk3HvDiheSeXEVmSqZamTnuMs4=/54x80/dkpu1ddg7pbsk.cloudfront.net/movie/11/20/20/11202098_ori.jpg",
        "original": "http://resizing.flixster.com/bvk3HvDiheSeXEVmSqZamTnuMs4=/54x80/dkpu1ddg7pbsk.cloudfront.net/movie/11/20/20/11202098_ori.jpg"
      },
      "abridged_cast": [
        {
          "name": "Anne Hathaway",
          "id": "162656190",
          "characters": [
            "Jules Ostin"
          ]
        },
        {
          "name": "Robert De Niro",
          "id": "162655521",
          "characters": [
            "Ben Whittaker"
          ]
        },
        {
          "name": "Rene Russo",
          "id": "162654462",
          "characters": [
            "Fiona"
          ]
        },
        {
          "name": "Adam DeVine",
          "id": "771395925",
          "characters": [
            "Jason"
          ]
        },
        {
          "name": "Andrew Rannells",
          "id": "770812771",
          "characters": [
            "Cameron"
          ]
        }
      ],
      "alternate_ids": {
        "imdb": "2361509"
      },
      "links": {
        "self": "http://api.rottentomatoes.com/api/public/v1.0/movies/771370466.json",
        "alternate": "http://www.rottentomatoes.com/m/the_intern/",
        "cast": "http://api.rottentomatoes.com/api/public/v1.0/movies/771370466/cast.json",
        "reviews": "http://api.rottentomatoes.com/api/public/v1.0/movies/771370466/reviews.json",
        "similar": "http://api.rottentomatoes.com/api/public/v1.0/movies/771370466/similar.json"
      }
    },
    {
      "id": "771419173",
      "title": "By The Sea",
      "year": 2015,
      "mpaa_rating": "R",
      "runtime": 132,
      "critics_consensus": "",
      "release_dates": {
        "theater": "2015-11-13"
      },
      "ratings": {
        "critics_rating": "Rotten",
        "critics_score": 27,
        "audience_rating": "Spilled",
        "audience_score": 52
      },
      "synopsis": "A married couple takes a vacation in France in the 1970s and find that their time in a sleepy seaside town, complete with a unique array of locals, strengthens their bond and reaffirms their marriage.",
      "posters": {
        "thumbnail": "http://resizing.flixster.com/tndThWj1jaa_Fo3-EN1eoaVw6kQ=/51x81/dkpu1ddg7pbsk.cloudfront.net/movie/11/19/18/11191829_ori.jpg",
        "profile": "http://resizing.flixster.com/tndThWj1jaa_Fo3-EN1eoaVw6kQ=/51x81/dkpu1ddg7pbsk.cloudfront.net/movie/11/19/18/11191829_ori.jpg",
        "detailed": "http://resizing.flixster.com/tndThWj1jaa_Fo3-EN1eoaVw6kQ=/51x81/dkpu1ddg7pbsk.cloudfront.net/movie/11/19/18/11191829_ori.jpg",
        "original": "http://resizing.flixster.com/tndThWj1jaa_Fo3-EN1eoaVw6kQ=/51x81/dkpu1ddg7pbsk.cloudfront.net/movie/11/19/18/11191829_ori.jpg"
      },
      "abridged_cast": [
        {
          "name": "Angelina Jolie",
          "id": "162652626",
          "characters": [
            "Vanessa"
          ]
        },
        {
          "name": "Brad Pitt",
          "id": "162652627",
          "characters": [
            "Roland"
          ]
        },
        {
          "name": "Melanie Laurent",
          "id": "351527317",
          "characters": [
            "Lea"
          ]
        },
        {
          "name": "Melvil Poupaud",
          "id": "326433086",
          "characters": [
            "Francois"
          ]
        },
        {
          "name": "Niels Arestrup",
          "id": "266555632",
          "characters": [
            "Bar Keeper"
          ]
        }
      ],
      "links": {
        "self": "http://api.rottentomatoes.com/api/public/v1.0/movies/771419173.json",
        "alternate": "http://www.rottentomatoes.com/m/by_the_sea_2015/",
        "cast": "http://api.rottentomatoes.com/api/public/v1.0/movies/771419173/cast.json",
        "reviews": "http://api.rottentomatoes.com/api/public/v1.0/movies/771419173/reviews.json",
        "similar": "http://api.rottentomatoes.com/api/public/v1.0/movies/771419173/similar.json"
      }
    },
    {
      "id": "771385978",
      "title": "The Last Witch Hunter",
      "year": 2015,
      "mpaa_rating": "PG-13",
      "runtime": 105,
      "critics_consensus": "",
      "release_dates": {
        "theater": "2015-10-23"
      },
      "ratings": {
        "critics_rating": "Rotten",
        "critics_score": 16,
        "audience_rating": "Spilled",
        "audience_score": 49
      },
      "synopsis": "The modern world holds many secrets, but the most astounding secret of all is that witches still live amongst us; vicious supernatural creatures intent on unleashing the Black Death upon the world. Armies of witch hunters battled the unnatural enemy across the globe for centuries, including KAULDER, a valiant warrior who managed to slay the all-powerful QUEEN WITCH, decimating her followers in the process. In the moments right before her death, the QUEEN curses KAULDER with her own immortality, forever separating him from his beloved wife and daughter in the afterlife. Today KAULDER is the only one of his kind remaining, and has spent centuries hunting down rogue witches, all the while yearning for his long-lost loved ones. However, unbeknownst to KAULDER, the QUEEN WITCH is resurrected and seeks revenge on her killer causing an epic battle that will determine the survival of the human race. (C) Summit",
      "posters": {
        "thumbnail": "http://resizing.flixster.com/6fWtO-VKnCprVBaWS_CiR6VxS3c=/53x81/dkpu1ddg7pbsk.cloudfront.net/movie/11/20/33/11203315_ori.jpg",
        "profile": "http://resizing.flixster.com/6fWtO-VKnCprVBaWS_CiR6VxS3c=/53x81/dkpu1ddg7pbsk.cloudfront.net/movie/11/20/33/11203315_ori.jpg",
        "detailed": "http://resizing.flixster.com/6fWtO-VKnCprVBaWS_CiR6VxS3c=/53x81/dkpu1ddg7pbsk.cloudfront.net/movie/11/20/33/11203315_ori.jpg",
        "original": "http://resizing.flixster.com/6fWtO-VKnCprVBaWS_CiR6VxS3c=/53x81/dkpu1ddg7pbsk.cloudfront.net/movie/11/20/33/11203315_ori.jpg"
      },
      "abridged_cast": [
        {
          "name": "Vin Diesel",
          "id": "162652472",
          "characters": [
            "Kaulder"
          ]
        },
        {
          "name": "Elijah Wood",
          "id": "162652512",
          "characters": [
            "Dolan 37th"
          ]
        },
        {
          "name": "Rose Leslie",
          "id": "771365481",
          "characters": [
            "Chloe"
          ]
        },
        {
          "name": "Michael Caine",
          "id": "162652646",
          "characters": [
            "Dolan 36th"
          ]
        },
        {
          "name": "Olafur Darri Olafsson",
          "id": "623770119",
          "characters": [
            "Belial"
          ]
        }
      ],
      "alternate_ids": {
        "imdb": "1618442"
      },
      "links": {
        "self": "http://api.rottentomatoes.com/api/public/v1.0/movies/771385978.json",
        "alternate": "http://www.rottentomatoes.com/m/the_last_witch_hunter/",
        "cast": "http://api.rottentomatoes.com/api/public/v1.0/movies/771385978/cast.json",
        "reviews": "http://api.rottentomatoes.com/api/public/v1.0/movies/771385978/reviews.json",
        "similar": "http://api.rottentomatoes.com/api/public/v1.0/movies/771385978/similar.json"
      }
    }
  ],
  "links": {
    "self": "http://api.rottentomatoes.com/api/public/v1.0/lists/movies/in_theaters.json?page_limit=25&country=us&page=1",
    "next": "http://api.rottentomatoes.com/api/public/v1.0/lists/movies/in_theaters.json?page_limit=25&country=us&page=2",
    "alternate": "http://www.rottentomatoes.com/movie/in_theaters"
  },
  "link_template": "http://api.rottentomatoes.com/api/public/v1.0/lists/movies/in_theaters.json?page_limit={results_per_page}&page={page_number}&country={country-code}"
}
